bw_simapro_csv/__init__.py
bw_simapro_csv/brightway.py
bw_simapro_csv/cas.py
bw_simapro_csv/constants.py
bw_simapro_csv/csv_reader.py
bw_simapro_csv/errors.py
bw_simapro_csv/header.py
bw_simapro_csv/main.py
bw_simapro_csv/parameters.py
bw_simapro_csv/uncertainty.py
bw_simapro_csv/units.py
bw_simapro_csv/utils.py
bw_simapro_csv/blocks/__init__.py
bw_simapro_csv/blocks/base.py
bw_simapro_csv/blocks/calculated_parameters.py
bw_simapro_csv/blocks/damage_category.py
bw_simapro_csv/blocks/generic_biosphere.py
bw_simapro_csv/blocks/impact_category.py
bw_simapro_csv/blocks/literature_reference.py
bw_simapro_csv/blocks/method.py
bw_simapro_csv/blocks/normalization_weighting_set.py
bw_simapro_csv/blocks/parameters.py
bw_simapro_csv/blocks/process.py
bw_simapro_csv/blocks/products.py
bw_simapro_csv/blocks/quantities.py
bw_simapro_csv/blocks/system_description.py
bw_simapro_csv/blocks/technosphere_edges.py
bw_simapro_csv/blocks/units.py
bw_simapro_csv/blocks/wastes.py
bw_simapro_csv-0.4.3.dist-info/licenses/LICENSE
bw_simapro_csv-0.4.3.dist-info/METADATA
bw_simapro_csv-0.4.3.dist-info/WHEEL
bw_simapro_csv-0.4.3.dist-info/top_level.txt
bw_simapro_csv-0.4.3.dist-info/RECORD
