Metadata-Version: 2.4
Name: bw_simapro_csv
Version: 0.4.3
Summary: Utility library to read and parse SimaPro CSV LCI and LCIA files
Author-email: bw_simapro_csv <cmutel@gmail.com>
Maintainer-email: bw_simapro_csv <cmutel@gmail.com>
Project-URL: source, https://github.com/brightway-lca/bw_simapro_csv
Project-URL: homepage, https://github.com/brightway-lca/bw_simapro_csv
Project-URL: tracker, https://github.com/brightway-lca/bw_simapro_csv/issues
Classifier: Development Status :: 4 - Beta
Classifier: Programming Language :: Python
Classifier: Programming Language :: Python :: 3
Classifier: Programming Language :: Python :: 3.9
Classifier: Programming Language :: Python :: 3.10
Classifier: Programming Language :: Python :: 3.11
Classifier: Programming Language :: Python :: 3.12
Classifier: Natural Language :: English
Classifier: Operating System :: OS Independent
Classifier: Topic :: Scientific/Engineering
Requires-Python: >=3.9
License-File: LICENSE
Requires-Dist: bw2parameters
Requires-Dist: multifunctional>=0.7.1
Requires-Dist: ftfy
Requires-Dist: loguru
Requires-Dist: platformdirs
Requires-Dist: pydantic
Requires-Dist: python-dateutil
Requires-Dist: stats_arrays
Provides-Extra: brightway
Requires-Dist: bw2data>=4.0.dev42; extra == "brightway"
Requires-Dist: bw2io>=0.9.dev27; extra == "brightway"
Provides-Extra: testing
Requires-Dist: bw_simapro_csv; extra == "testing"
Requires-Dist: pytest; extra == "testing"
Requires-Dist: pytest-cov; extra == "testing"
Requires-Dist: pytest-randomly; extra == "testing"
Requires-Dist: python-coveralls; extra == "testing"
Provides-Extra: dev
Requires-Dist: build; extra == "dev"
Requires-Dist: pre-commit; extra == "dev"
Requires-Dist: black; extra == "dev"
Requires-Dist: isort; extra == "dev"
Requires-Dist: pylint; extra == "dev"
Requires-Dist: pytest; extra == "dev"
Requires-Dist: pytest-cov; extra == "dev"
Requires-Dist: pytest-randomly; extra == "dev"
Requires-Dist: setuptools; extra == "dev"
Dynamic: license-file
